llama_index/tools/chatgpt_plugin/__init__.py
llama_index/tools/chatgpt_plugin/base.py
llama_index_tools_chatgpt_plugin-0.4.1.dist-info/METADATA
llama_index_tools_chatgpt_plugin-0.4.1.dist-info/WHEEL
llama_index_tools_chatgpt_plugin-0.4.1.dist-info/licenses/LICENSE
llama_index_tools_chatgpt_plugin-0.4.1.dist-info/RECORD
